{"watermark":"V2604","generated_on":"da2.eecs.utk.edu","conventions":{"format":"';'-separated, gzip, LC_ALL=C-sorted by first key","present_not_valid":"A <=1KB gzip shard is an empty never-built table \u2014 flagged valid:false, never offered as a source."},"cost_model":{"read_mb_s_per_core":250,"cores":{"da3":8,"isaac":40},"split_multiplier":4,"note":"Estimates only \u2014 use the Calibrate command to time one shard and rescale."},"synonyms":{"A":["canonical author","aliased author","developer id"],"a":["raw author","author string"],"C":["canonical committer"],"c":["raw committer"],"P":["deforked project","canonical project"],"p":["project"],"project":["repo","P","canonical project"],"commit":["sha1","c2*"],"blob":["content","b2*"],"atime":["author time","time"],"ctime":["commit time"],"sigtype":["signature","signed"],"tree":["dir"],"newblob":["blob"],"oldblob":["blob"],"filepath":["file","path"]},"tables":[{"name":"c2datFull","axis":"commit","key":"commit(sha1 hex)","schema":["commit","tree","parent","author","committer","atime","ctime","atz","ctz","msg"],"shard":{"count":128,"by":"sha1 hex prefix","sorted_by":"commit"},"row_scale":"~5.87e9 (1 / commit)","producer":"roots-c2ta.slurm:c2dat (lstCmt.perl 9)","consumers":["c2sigFull","c2dAtFull","commit_v2604 (join)"],"notes":"RAW author/committer strings. Tier-1 root table.","seed_valid":true,"store":"flat","access":null,"locations":[{"tier":"da","host":"da0\u2013da5","path":"/da7_data/basemaps/gz/c2datFull.V2604.$i.s","verified":true,"bytes_per_shard":10287810791},{"tier":"isaac","host":"isaac","path":"~/work1/gz/c2datFull.V2604.$i.s"}],"scanned":true,"bytes_per_shard":10287810791,"total_bytes":1316839781248,"valid":true},{"name":"c2dAtFull","axis":"commit","key":"commit(sha1 hex)","schema":["commit","tree","parent","A","C","atime","ctime","atz","ctz","msg"],"shard":{"count":128,"by":"sha1 hex prefix","sorted_by":"commit"},"row_scale":"~5.87e9 (1 / commit)","producer":null,"consumers":[],"notes":"A / C = canonical (aliased) author & committer.","seed_valid":true,"store":"flat","access":null,"locations":[{"tier":"da","host":"da0\u2013da5","path":"/da7_data/basemaps/gz/c2dAtFull.V2604.$i.s","verified":true,"bytes_per_shard":10396817182},{"tier":"isaac","host":"isaac","path":"~/work1/gz/c2dAtFull.V2604.$i.s"}],"scanned":true,"bytes_per_shard":10396817182,"total_bytes":1330792599296,"valid":true},{"name":"agc2datFull","axis":"commit","key":"commit(sha1 hex)","schema":["commit","project","tree","parent","author","committer","atime","ctime","atz","ctz","msg"],"shard":{"count":128,"by":"sha1 hex prefix","sorted_by":"commit"},"row_scale":null,"producer":null,"consumers":["commit_v2604 (direct import alt.)"],"notes":"Already carries project (field 2) + full __NEWLINE__-encoded msg \u2014 the materialized c2ch shape.","seed_valid":true,"store":"flat","access":null,"locations":[{"tier":"da","host":"da0\u2013da5","path":"/da5_data/basemaps/gz/agc2datFull.V2604.$i.s","verified":true,"bytes_per_shard":644450683}],"scanned":true,"bytes_per_shard":644450683,"total_bytes":82489687424,"valid":true},{"name":"c2aAcCtFull","axis":"commit","key":"commit(sha1 hex)","schema":["commit","a","A","c","C","atime"],"shard":{"count":128,"by":"sha1 hex prefix","sorted_by":"commit"},"row_scale":null,"producer":null,"consumers":[],"notes":"Lean identity: raw + canonical author and committer.","seed_valid":true,"store":"flat","access":null,"locations":[{"tier":"da","host":"da0\u2013da5","path":"/da7_data/basemaps/gz/c2aAcCtFull.V2604.$i.s","verified":true,"bytes_per_shard":2912380475},{"tier":"isaac","host":"isaac","path":"~/work1/gz/c2aAcCtFull.V2604.$i.s"}],"scanned":true,"bytes_per_shard":2912380475,"total_bytes":372784700800,"valid":true},{"name":"c2fbbFull","axis":"commit","key":"commit(sha1 hex)","schema":["commit","filepath","newblob","oldblob"],"shard":{"count":128,"by":"sha1 hex prefix","sorted_by":"commit"},"row_scale":null,"producer":null,"consumers":[],"notes":"File-blob deltas per commit (many rows / commit).","seed_valid":true,"store":"flat","access":null,"locations":[{"tier":"da","host":"da0\u2013da5","path":"/da7_data/basemaps/gz/c2fbbFull.V2604.$i.s","verified":true,"bytes_per_shard":49735359092},{"tier":"isaac","host":"isaac","path":"~/work1/gz/c2fbbFull.V2604.$i.s"}],"scanned":true,"bytes_per_shard":49735359092,"total_bytes":6366125963776,"valid":true},{"name":"c2pFull","axis":"commit","key":"commit(sha1 hex)","schema":["commit","project"],"shard":{"count":100,"by":"sha1 hex prefix","sorted_by":"commit"},"row_scale":null,"producer":null,"consumers":["commit_v2604 (join)"],"notes":"Raw; MULTIPLE projects per commit, commit-sorted. Reduce with awk '$1!=p' for one project/commit.","seed_valid":true,"store":"flat","access":null,"locations":[{"tier":"da","host":"da0\u2013da5","path":"/da7_data/basemaps/gz/c2pFull.V2604.$i.s","verified":true,"bytes_per_shard":12923778620},{"tier":"isaac","host":"isaac","path":"~/work1/gz/c2pFull.V2604.$i.s"}],"scanned":true,"bytes_per_shard":12923778620,"total_bytes":1292377862000,"valid":true},{"name":"c2PAtFull","axis":"commit","key":"commit(sha1 hex)","schema":["commit","project","A","atime"],"shard":{"count":128,"by":"sha1 hex prefix","sorted_by":"commit"},"row_scale":null,"producer":null,"consumers":[],"notes":"Commit \u2192 deforked project + canonical author + author time.","seed_valid":true,"store":"flat","access":null,"locations":[{"tier":"da","host":"da0\u2013da5","path":"/da7_data/basemaps/gz/c2PAtFull.V2604.$i.s"},{"tier":"isaac","host":"isaac","path":"~/work1/gz/c2PAtFull.V2604.$i.s"}],"scanned":false,"bytes_per_shard":null,"total_bytes":null,"valid":true},{"name":"c2sigFull","axis":"commit","key":"commit(sha1 hex)","schema":["commit","sigtype"],"shard":{"count":128,"by":"sha1 hex prefix","sorted_by":"commit"},"row_scale":null,"producer":null,"consumers":[],"notes":"Signed commits only (sigtype \u2208 gpg/ssh/\u2026).","seed_valid":true,"store":"flat","access":null,"locations":[{"tier":"da","host":"da0\u2013da5","path":"/da7_data/basemaps/gz/c2sigFull.V2604.$i.s"},{"tier":"isaac","host":"isaac","path":"~/work1/gz/c2sigFull.V2604.$i.s"}],"scanned":false,"bytes_per_shard":null,"total_bytes":null,"valid":true},{"name":"c2chFull","axis":"commit","key":"commit(sha1 hex)","schema":["commit","project","tree","parent","author","committer","atime","ctime","atz","ctz","comment"],"shard":{"count":128,"by":"sha1 hex prefix","sorted_by":"commit"},"row_scale":null,"producer":null,"consumers":[],"notes":"EMPTY for V2604 \u2014 never built (20-byte gzip). Do NOT use; reproduce by dynamic join (c2pFull \u22c8 c2datFull).","seed_valid":false,"store":"flat","access":null,"locations":[{"tier":"da","host":"da0\u2013da5","path":"/da7_data/basemaps/gz/c2chFull.V2604.$i.s","verified":true,"bytes_per_shard":20}],"scanned":true,"bytes_per_shard":20,"total_bytes":2560,"valid":false},{"name":"p2cFull","axis":"project","key":"project","schema":["project","commit"],"shard":{"count":128,"by":"project hash","sorted_by":"project"},"row_scale":null,"producer":null,"consumers":[],"notes":"Inverse of c2pFull, project-sorted.","seed_valid":true,"store":"flat","access":null,"locations":[{"tier":"da","host":"da0\u2013da5","path":"/da7_data/basemaps/gz/p2cFull.V2604.$i.s","verified":true,"bytes_per_shard":35175458619},{"tier":"isaac","host":"isaac","path":"~/work1/gz/p2cFull.V2604.$i.s"}],"scanned":true,"bytes_per_shard":35175458619,"total_bytes":4502458703232,"valid":true},{"name":"p2PFull","axis":"project","key":"rawrepo","schema":["rawrepo","canonicalProject"],"shard":{"count":2,"by":"single","sorted_by":"rawrepo"},"row_scale":null,"producer":null,"consumers":[],"notes":"Deforking map: raw repo \u2192 canonical project.","seed_valid":true,"store":"flat","access":null,"locations":[{"tier":"da","host":"da0\u2013da5","path":"/da5_data/basemaps/gz/p2PFull.V2604.s","verified":true,"bytes_per_shard":3293374968},{"tier":"isaac","host":"isaac","path":"~/work1/gz/p2PFull.V2604.s"}],"scanned":true,"bytes_per_shard":3293374968,"total_bytes":6586749936,"valid":true},{"name":"a2PFull","axis":"author","key":"A","schema":["A","project"],"shard":{"count":32,"by":"A hash","sorted_by":"A"},"row_scale":null,"producer":null,"consumers":[],"notes":"Canonical author \u2192 project.","seed_valid":true,"store":"flat","access":null,"locations":[{"tier":"da","host":"da0\u2013da5","path":"/da7_data/basemaps/gz/a2PFull.V2604.$i.s","verified":true,"bytes_per_shard":179107311},{"tier":"isaac","host":"isaac","path":"~/work1/gz/a2PFull.V2604.$i.s"}],"scanned":true,"bytes_per_shard":179107311,"total_bytes":5731433952,"valid":true},{"name":"P2aFull","axis":"author","key":"project","schema":["project","A"],"shard":{"count":32,"by":"A hash","sorted_by":"project"},"row_scale":null,"producer":null,"consumers":[],"notes":"Project \u2192 canonical author (author-hash sharded).","seed_valid":true,"store":"flat","access":null,"locations":[{"tier":"da","host":"da0\u2013da5","path":"/da7_data/basemaps/gz/P2aFull.V2604.$i.s","verified":true,"bytes_per_shard":222568555},{"tier":"isaac","host":"isaac","path":"~/work1/gz/P2aFull.V2604.$i.s"}],"scanned":true,"bytes_per_shard":222568555,"total_bytes":7122193760,"valid":true},{"name":"A2clsFull","axis":"author","key":"A","schema":["A","class","privacy","evidence","nIds","nCmt"],"shard":{"count":32,"by":"A hash","sorted_by":"A"},"row_scale":null,"producer":null,"consumers":[],"notes":"Per-id classification (A2cls dataset). class \u2208 developer/bot/bad/local.","seed_valid":true,"store":"flat","access":null,"locations":[{"tier":"da","host":"da0\u2013da5","path":"/da5_data/basemaps/gz/A2clsFull.V2604.$i.s","verified":true,"bytes_per_shard":36160600},{"tier":"isaac","host":"isaac","path":"~/work1/gz/A2clsFull.V2604.$i.s"}],"scanned":true,"bytes_per_shard":36160600,"total_bytes":1157139200,"valid":true},{"name":"A2mncFull","axis":"author","key":"A","schema":["A","m","n","c"],"shard":{"count":32,"by":"A hash","sorted_by":"A"},"row_scale":null,"producer":null,"consumers":[],"notes":"Author message/name/commit counts.","seed_valid":true,"store":"flat","access":null,"locations":[{"tier":"isaac","host":"isaac","path":"~/work1/gz/A2mncFull.V2604.$i.s"}],"scanned":false,"bytes_per_shard":null,"total_bytes":null,"valid":true},{"name":"key2AFull","axis":"author","key":"keyid16","schema":["keyid16","A"],"shard":{"count":1,"by":"single","sorted_by":"keyid16"},"row_scale":null,"producer":null,"consumers":[],"notes":"Signing key \u2192 author (586k signed keys).","seed_valid":true,"store":"flat","access":null,"locations":[{"tier":"isaac","host":"isaac","path":"~/work1/gz/key2AFull.V2604.s"}],"scanned":false,"bytes_per_shard":null,"total_bytes":null,"valid":true},{"name":"key2fanoutFull","axis":"author","key":"keyid16","schema":["keyid16","fanout"],"shard":{"count":1,"by":"single","sorted_by":"keyid16"},"row_scale":null,"producer":null,"consumers":[],"notes":"Signing-key fan-out (# authors per key).","seed_valid":true,"store":"flat","access":null,"locations":[{"tier":"isaac","host":"isaac","path":"~/work1/gz/key2fanoutFull.V2604.s"}],"scanned":false,"bytes_per_shard":null,"total_bytes":null,"valid":true},{"name":"A2summFull","axis":"author","key":"A","schema":["A","summ(json)"],"shard":{"count":32,"by":"A hash","sorted_by":"A"},"row_scale":null,"producer":null,"consumers":[],"notes":"Per-author Mongo-style summary JSON. EMPTY for V2604 shards \u2192 rebuild before use.","seed_valid":false,"store":"flat","access":null,"locations":[{"tier":"da","host":"da0\u2013da5","path":"/da3_data/basemaps/gz/A2summFullV2604.$i.s"}],"scanned":false,"bytes_per_shard":null,"total_bytes":null,"valid":false},{"name":"b2fACcFull","axis":"blob","key":"blob","schema":["blob","t","A","C","commit"],"shard":{"count":128,"by":"blob hash","sorted_by":"blob"},"row_scale":null,"producer":null,"consumers":[],"notes":"First blob provenance: earliest time, author, committer, commit.","seed_valid":true,"store":"flat","access":null,"locations":[{"tier":"isaac","host":"isaac","path":"~/work1/gz/b2fACcFull.V2604.$i.s"}],"scanned":false,"bytes_per_shard":null,"total_bytes":null,"valid":true},{"name":"b2tACcFull","axis":"blob","key":"blob","schema":["blob","t","A","C","commit"],"shard":{"count":128,"by":"blob hash","sorted_by":"blob"},"row_scale":null,"producer":null,"consumers":[],"notes":"Blob \u2192 time/author/committer/commit (tree axis).","seed_valid":true,"store":"flat","access":null,"locations":[{"tier":"isaac","host":"isaac","path":"~/work1/gz/b2tACcFull.V2604.$i.s"}],"scanned":false,"bytes_per_shard":null,"total_bytes":null,"valid":true},{"name":"A_metadata","axis":"author","key":"A","schema":["A","(document fields)"],"shard":{"count":1,"by":"single","sorted_by":"A"},"row_scale":null,"producer":null,"consumers":[],"notes":"Per-author metadata documents.","seed_valid":true,"store":"mongo","access":"ssh da3 'mongosh --quiet WoC --eval \"db[\\\"A_metadata.V2604\\\"].findOne({_id:<A>})\"'","locations":[{"tier":"mongo","host":"da3","path":"WoC.A_metadata.V2604"}],"scanned":false,"bytes_per_shard":null,"total_bytes":null,"valid":true},{"name":"P_metadata","axis":"project","key":"project","schema":["project","(document fields)"],"shard":{"count":1,"by":"single","sorted_by":"project"},"row_scale":null,"producer":null,"consumers":[],"notes":"Per-project metadata documents.","seed_valid":true,"store":"mongo","access":"ssh da3 'mongosh --quiet WoC --eval \"db[\\\"P_metadata.V2604\\\"].findOne({_id:<project>})\"'","locations":[{"tier":"mongo","host":"da3","path":"WoC.P_metadata.V2604"}],"scanned":false,"bytes_per_shard":null,"total_bytes":null,"valid":true},{"name":"commit_v2604","axis":"commit","key":"commit(sha1 hex)","schema":["sha1","time","tc","tree","parent","taz","tcz","author","commiter","project","comment"],"shard":{"count":1,"by":"single","sorted_by":"time"},"row_scale":"~5.82e9 rows (INT32 time min..max)","producer":"dynamic join c2pFull \u22c8 c2datFull \u2192 chImportCmt.perl \u2192 INSERT RowBinary","consumers":[],"notes":"MergeTree ORDER BY time. Built from a streaming join, not a stored c2chFull.","seed_valid":true,"store":"clickhouse","access":"ssh da3 'clickhouse-client -q \"SELECT \u2026 FROM commit_v2604 WHERE time BETWEEN \u2026 LIMIT 20\"'","locations":[{"tier":"clickhouse","host":"da3","path":"commit_v2604"}],"scanned":false,"bytes_per_shard":null,"total_bytes":null,"valid":true},{"name":"edges.typed","axis":"edge","key":"src(type,id)","schema":["srctype","srcid","relation","dsttype","dstid","weight","source"],"shard":{"count":1,"by":"single","sorted_by":"srctype"},"row_scale":"69,758,902 edges","producer":null,"consumers":[],"notes":"Cross-corpus heterogeneous graph: P\u00b7D\u00b7A\u00b7S\u00b7K\u00b7I nodes; DEPENDS_ON/MENTIONS_DOI/HAS_AUTHOR/\u2026 relations. Powers the Impact Explorer.","seed_valid":true,"store":"graph","access":"zcat cite-sw/graph/edges.typed.gz","locations":[{"tier":"graph","host":"ssc-oscar/cite-sw","path":"graph/edges.typed.gz"}],"scanned":false,"bytes_per_shard":null,"total_bytes":null,"valid":true},{"name":"agc2fbb","axis":"commit","key":"commit(sha1 hex)","schema":["commit","filepath","newblob","oldblob"],"shard":{"count":128,"by":"sha1 hex prefix","sorted_by":"commit"},"row_scale":null,"producer":null,"consumers":[],"notes":"agg c2fbb with project scope (auto-discovered; not in the curated seed).","seed_valid":true,"store":"flat","access":null,"locations":[{"tier":"da","host":"da0\u2013da5","path":"/da5_data/basemaps/gz/agc2fbb.V2604.$i.s","verified":true,"bytes_per_shard":127118616}],"scanned":true,"bytes_per_shard":127118616,"total_bytes":16271182848,"valid":true,"discovered":true},{"name":"agc2pFull","axis":"commit","key":"commit(sha1 hex)","schema":["commit","project"],"shard":{"count":128,"by":"sha1 hex prefix","sorted_by":"commit"},"row_scale":null,"producer":null,"consumers":[],"notes":"aggregated commit\u2192project (auto-discovered; not in the curated seed).","seed_valid":true,"store":"flat","access":null,"locations":[{"tier":"da","host":"da0\u2013da5","path":"/da5_data/basemaps/gz/agc2pFull.V2604.$i.s","verified":true,"bytes_per_shard":119687121}],"scanned":true,"bytes_per_shard":119687121,"total_bytes":15319951488,"valid":true,"discovered":true},{"name":"aFull","axis":"author","key":"a","schema":["a(raw author string)"],"shard":{"count":1,"by":"single","sorted_by":"a"},"row_scale":null,"producer":null,"consumers":[],"notes":"raw-author dictionary (auto-discovered; not in the curated seed).","seed_valid":true,"store":"flat","access":null,"locations":[{"tier":"da","host":"da0\u2013da5","path":"/da5_data/basemaps/gz/aFull.V2604.s","verified":true,"bytes_per_shard":1332547014}],"scanned":true,"bytes_per_shard":1332547014,"total_bytes":1332547014,"valid":true,"discovered":true},{"name":"pFull","axis":"project","key":"project","schema":["project"],"shard":{"count":1,"by":"single","sorted_by":"project"},"row_scale":null,"producer":null,"consumers":[],"notes":"project dictionary (auto-discovered; not in the curated seed).","seed_valid":true,"store":"flat","access":null,"locations":[{"tier":"da","host":"da0\u2013da5","path":"/da5_data/basemaps/gz/pFull.V2604.s","verified":true,"bytes_per_shard":2134104110}],"scanned":true,"bytes_per_shard":2134104110,"total_bytes":2134104110,"valid":true,"discovered":true},{"name":"flFull","axis":"commit","key":"forgelang","schema":["forge/lang","count"],"shard":{"count":1,"by":"single","sorted_by":"forge/lang"},"row_scale":null,"producer":null,"consumers":[],"notes":"forge/language rollup (auto-discovered; not in the curated seed).","seed_valid":true,"store":"flat","access":null,"locations":[{"tier":"da","host":"da0\u2013da5","path":"/da5_data/basemaps/gz/flFull.V2604.s","verified":true,"bytes_per_shard":97289699}],"scanned":true,"bytes_per_shard":97289699,"total_bytes":97289699,"valid":true,"discovered":true},{"name":"pOld2pNew","axis":"project","key":"project","schema":["projectOld","projectNew"],"shard":{"count":1,"by":"single","sorted_by":"projectOld"},"row_scale":null,"producer":null,"consumers":[],"notes":"project rename/migration map (auto-discovered; not in the curated seed).","seed_valid":true,"store":"flat","access":null,"locations":[{"tier":"da","host":"da0\u2013da5","path":"/da5_data/basemaps/gz/pOld2pNew.V2604.s","verified":true,"bytes_per_shard":6289391625}],"scanned":true,"bytes_per_shard":6289391625,"total_bytes":6289391625,"valid":true,"discovered":true}]}